server.py
douyin_mcp_server_zdy-0.1.0.dist-info/METADATA
douyin_mcp_server_zdy-0.1.0.dist-info/WHEEL
douyin_mcp_server_zdy-0.1.0.dist-info/entry_points.txt
douyin_mcp_server_zdy-0.1.0.dist-info/top_level.txt
douyin_mcp_server_zdy-0.1.0.dist-info/RECORD
