Metadata-Version: 2.4
Name: douyin-mcp-server-zdy
Version: 0.1.0
Summary: MCP server for downloading Douyin videos and extracting text
Classifier: Development Status :: 3 - Alpha
Classifier: Intended Audience :: Developers
Classifier: License :: OSI Approved :: MIT License
Classifier: Programming Language :: Python :: 3
Classifier: Programming Language :: Python :: 3.10
Classifier: Programming Language :: Python :: 3.11
Classifier: Programming Language :: Python :: 3.12
Requires-Python: >=3.13
Requires-Dist: dashscope>=1.25.8
Requires-Dist: ffmpeg-python>=0.2.0
Requires-Dist: mcp[fastmcp]>=1.25.0
Requires-Dist: requests>=2.32.5
Requires-Dist: tqdm>=4.67.1
